[{
  "_id": 1,
  "description": "SAVING",
  "maintenanceFee": 0,
  "monthlyTransactionLimit": 30,
  "transactionDay": 0,
  "openingAmount": 0,
  "isDelete": false,
  "_class": "com.example.bank.model.ProductTypeModel"
},
{
  "_id": 2,
  "description": "CURRENT",
  "maintenanceFee": 5,
  "monthlyTransactionLimit": 0,
  "transactionDay": 0,
  "openingAmount": 0,
  "isDelete": false,
  "_class": "com.example.bank.model.ProductTypeModel"
},
{
  "_id": 3,
  "description": "FIXED_TERM",
  "maintenanceFee": 0,
  "monthlyTransactionLimit": 1,
  "transactionDay": 15,
  "openingAmount": 0,
  "isDelete": false,
  "_class": "com.example.bank.model.ProductTypeModel"
},
{
  "_id": 4,
  "description": "PERSONAL",
  "maintenanceFee": 0,
  "monthlyTransactionLimit": 0,
  "transactionDay": 0,
  "openingAmount": 0,
  "isDelete": false,
  "_class": "com.example.bank.model.ProductTypeModel"
},
{
  "_id": 5,
  "description": "BUSINESS",
  "maintenanceFee": 0,
  "monthlyTransactionLimit": 0,
  "transactionDay": 0,
  "openingAmount": 0,
  "isDelete": false,
  "_class": "com.example.bank.model.ProductTypeModel"
},
{
  "_id": 6,
  "description": "CREDIT_CARD",
  "maintenanceFee": 0,
  "monthlyTransactionLimit": 30,
  "transactionDay": 0,
  "openingAmount": 0,
  "isDelete": false,
  "_class": "com.example.bank.model.ProductTypeModel"
}]